bm/integer_math/__init__.py
bm/integer_math/combinatorics.py
bm/integer_math/num_theory.py
bm/integer_math/py.typed
bm_integer_math-0.7.1.dist-info/licenses/LICENSE
bm_integer_math-0.7.1.dist-info/WHEEL
bm_integer_math-0.7.1.dist-info/METADATA
bm_integer_math-0.7.1.dist-info/RECORD
