Metadata-Version: 2.4
Name: bm.integer-math
Version: 0.7.1
Summary: Integer Mathematics
Keywords: comb,combinations,combinatorics,gcd,integer,lcm,math,number-theory,primes
Author-email: "Geoffrey R. Scheller" <geoffrey@scheller.com>
Requires-Python: >=3.12
Classifier: Development Status :: 3 - Alpha
Classifier: Framework :: Pytest
Classifier: Intended Audience :: Education
Classifier: Intended Audience :: Science/Research
Classifier: License :: OSI Approved :: Apache Software License
Classifier: Operating System :: OS Independent
Classifier: Programming Language :: Python :: 3.13
Classifier: Typing :: Typed
License-File: LICENSE
Requires-Dist: pythonic-fp.circular-array >= 5.1.0
Requires-Dist: pythonic-fp.fptools >= 3.0.0
Project-URL: Changelog, https://github.com/grscheller/bm-integer-math/blob/main/CHANGELOG.md
Project-URL: Documentation, https://grscheller.github.io/bm-docs/integer-math/
Project-URL: Homepage, https://github.com/grscheller/bm-docs/blob/main/README.md
Project-URL: Source, https://github.com/grscheller/bm-integer-math
